{
    "dependencies": {
        "github.com/aws/aws-sdk-go-v2": "v1.4.0",
        "github.com/aws/aws-sdk-go-v2/internal/configsources": "v0.0.0-00010101000000-000000000000",
        "github.com/aws/aws-sdk-go-v2/internal/endpoints/v2": "v2.0.0-00010101000000-000000000000",
        "github.com/aws/smithy-go": "v1.4.0"
    },
    "files": [
        "api_client.go",
        "api_client_test.go",
        "api_op_AssociateFraudster.go",
        "api_op_CreateDomain.go",
        "api_op_CreateWatchlist.go",
        "api_op_DeleteDomain.go",
        "api_op_DeleteFraudster.go",
        "api_op_DeleteSpeaker.go",
        "api_op_DeleteWatchlist.go",
        "api_op_DescribeDomain.go",
        "api_op_DescribeFraudster.go",
        "api_op_DescribeFraudsterRegistrationJob.go",
        "api_op_DescribeSpeaker.go",
        "api_op_DescribeSpeakerEnrollmentJob.go",
        "api_op_DescribeWatchlist.go",
        "api_op_DisassociateFraudster.go",
        "api_op_EvaluateSession.go",
        "api_op_ListDomains.go",
        "api_op_ListFraudsterRegistrationJobs.go",
        "api_op_ListFraudsters.go",
        "api_op_ListSpeakerEnrollmentJobs.go",
        "api_op_ListSpeakers.go",
        "api_op_ListTagsForResource.go",
        "api_op_ListWatchlists.go",
        "api_op_OptOutSpeaker.go",
        "api_op_StartFraudsterRegistrationJob.go",
        "api_op_StartSpeakerEnrollmentJob.go",
        "api_op_TagResource.go",
        "api_op_UntagResource.go",
        "api_op_UpdateDomain.go",
        "api_op_UpdateWatchlist.go",
        "auth.go",
        "deserializers.go",
        "doc.go",
        "endpoints.go",
        "endpoints_config_test.go",
        "endpoints_test.go",
        "generated.json",
        "internal/endpoints/endpoints.go",
        "internal/endpoints/endpoints_test.go",
        "options.go",
        "protocol_test.go",
        "serializers.go",
        "snapshot_test.go",
        "sra_operation_order_test.go",
        "types/enums.go",
        "types/errors.go",
        "types/types.go",
        "validators.go"
    ],
    "go": "1.22",
    "module": "github.com/aws/aws-sdk-go-v2/service/voiceid",
    "unstable": false
}
