{
    "dependencies": {
        "github.com/aws/aws-sdk-go-v2": "v1.4.0",
        "github.com/aws/aws-sdk-go-v2/internal/configsources": "v0.0.0-00010101000000-000000000000",
        "github.com/aws/aws-sdk-go-v2/internal/endpoints/v2": "v2.0.0-00010101000000-000000000000",
        "github.com/aws/smithy-go": "v1.4.0"
    },
    "files": [
        "api_client.go",
        "api_client_test.go",
        "api_op_AssociateAppBlockBuilderAppBlock.go",
        "api_op_AssociateApplicationFleet.go",
        "api_op_AssociateApplicationToEntitlement.go",
        "api_op_AssociateFleet.go",
        "api_op_BatchAssociateUserStack.go",
        "api_op_BatchDisassociateUserStack.go",
        "api_op_CopyImage.go",
        "api_op_CreateAppBlock.go",
        "api_op_CreateAppBlockBuilder.go",
        "api_op_CreateAppBlockBuilderStreamingURL.go",
        "api_op_CreateApplication.go",
        "api_op_CreateDirectoryConfig.go",
        "api_op_CreateEntitlement.go",
        "api_op_CreateFleet.go",
        "api_op_CreateImageBuilder.go",
        "api_op_CreateImageBuilderStreamingURL.go",
        "api_op_CreateStack.go",
        "api_op_CreateStreamingURL.go",
        "api_op_CreateThemeForStack.go",
        "api_op_CreateUpdatedImage.go",
        "api_op_CreateUsageReportSubscription.go",
        "api_op_CreateUser.go",
        "api_op_DeleteAppBlock.go",
        "api_op_DeleteAppBlockBuilder.go",
        "api_op_DeleteApplication.go",
        "api_op_DeleteDirectoryConfig.go",
        "api_op_DeleteEntitlement.go",
        "api_op_DeleteFleet.go",
        "api_op_DeleteImage.go",
        "api_op_DeleteImageBuilder.go",
        "api_op_DeleteImagePermissions.go",
        "api_op_DeleteStack.go",
        "api_op_DeleteThemeForStack.go",
        "api_op_DeleteUsageReportSubscription.go",
        "api_op_DeleteUser.go",
        "api_op_DescribeAppBlockBuilderAppBlockAssociations.go",
        "api_op_DescribeAppBlockBuilders.go",
        "api_op_DescribeAppBlocks.go",
        "api_op_DescribeApplicationFleetAssociations.go",
        "api_op_DescribeApplications.go",
        "api_op_DescribeDirectoryConfigs.go",
        "api_op_DescribeEntitlements.go",
        "api_op_DescribeFleets.go",
        "api_op_DescribeImageBuilders.go",
        "api_op_DescribeImagePermissions.go",
        "api_op_DescribeImages.go",
        "api_op_DescribeSessions.go",
        "api_op_DescribeStacks.go",
        "api_op_DescribeThemeForStack.go",
        "api_op_DescribeUsageReportSubscriptions.go",
        "api_op_DescribeUserStackAssociations.go",
        "api_op_DescribeUsers.go",
        "api_op_DisableUser.go",
        "api_op_DisassociateAppBlockBuilderAppBlock.go",
        "api_op_DisassociateApplicationFleet.go",
        "api_op_DisassociateApplicationFromEntitlement.go",
        "api_op_DisassociateFleet.go",
        "api_op_EnableUser.go",
        "api_op_ExpireSession.go",
        "api_op_ListAssociatedFleets.go",
        "api_op_ListAssociatedStacks.go",
        "api_op_ListEntitledApplications.go",
        "api_op_ListTagsForResource.go",
        "api_op_StartAppBlockBuilder.go",
        "api_op_StartFleet.go",
        "api_op_StartImageBuilder.go",
        "api_op_StopAppBlockBuilder.go",
        "api_op_StopFleet.go",
        "api_op_StopImageBuilder.go",
        "api_op_TagResource.go",
        "api_op_UntagResource.go",
        "api_op_UpdateAppBlockBuilder.go",
        "api_op_UpdateApplication.go",
        "api_op_UpdateDirectoryConfig.go",
        "api_op_UpdateEntitlement.go",
        "api_op_UpdateFleet.go",
        "api_op_UpdateImagePermissions.go",
        "api_op_UpdateStack.go",
        "api_op_UpdateThemeForStack.go",
        "auth.go",
        "deserializers.go",
        "doc.go",
        "endpoints.go",
        "endpoints_config_test.go",
        "endpoints_test.go",
        "generated.json",
        "internal/endpoints/endpoints.go",
        "internal/endpoints/endpoints_test.go",
        "options.go",
        "protocol_test.go",
        "serializers.go",
        "snapshot_test.go",
        "sra_operation_order_test.go",
        "types/enums.go",
        "types/errors.go",
        "types/types.go",
        "validators.go"
    ],
    "go": "1.22",
    "module": "github.com/aws/aws-sdk-go-v2/service/appstream",
    "unstable": false
}
